StefanTools/__init__.py
StefanTools/class_sText.py
StefanTools/errors.py
StefanTools/main.py
StefanTools/methods.py
StefanTools-1.4.1.dist-info/METADATA
StefanTools-1.4.1.dist-info/WHEEL
StefanTools-1.4.1.dist-info/top_level.txt
StefanTools-1.4.1.dist-info/RECORD
