Metadata-Version: 2.1
Name: StefanTools
Version: 1.4.1
Requires-Dist: rich
Requires-Dist: inputimeout
Requires-Dist: inflect
